{"py/object": "rasa.core.featurizers.tracker_featurizers.IntentMaxHistoryTrackerFeaturizer", "state_featurizer": {"py/object": "rasa.core.featurizers.single_state_featurizer.IntentTokenizerSingleStateFeaturizer", "_default_feature_states": {"intent": {"SolarBhai_platform": 0, "access_tickets_SolarBhai": 1, "additional_information_for_sites": 2, "affirm": 3, "ask_billing_info": 4, "ask_consumption_details": 5, "ask_question": 6, "assign_issues_to_team": 7, "assigne_roles_SolarBhai": 8, "back": 9, "benefits_solar_performance_management": 10, "bot_challenge": 11, "causes_solar_loss": 12, "causes_underperformance": 13, "contribution_AI": 14, "deny": 15, "factors_affect_generation_solar_power": 16, "faq_benefits_of_solar_energy": 17, "faq_solar_battery_storage": 18, "faq_solar_energy_environmental_impact": 19, "faq_solar_energy_future_outlook": 20, "faq_solar_inverter_maintenance": 21, "faq_solar_net_metering": 22, "faq_solar_panel_cleaning_frequency": 23, "faq_solar_panel_efficiency": 24, "faq_solar_panel_installation_process": 25, "faq_solar_panel_lifetime": 26, "faq_solar_panel_maintenance": 27, "faq_solar_panel_orientation": 28, "faq_solar_panel_shading_issues": 29, "faq_solar_power_incentives": 30, "faq_types_of_solar_panels": 31, "filter_display_additional_informations": 32, "get_question": 33, "goodbye": 34, "greet": 35, "improve_solar_power_performance": 36, "interact_with_tables": 37, "issues_solar_inverters": 38, "key_performance_indicators": 39, "losses_solar_power_plants": 40, "measure_performance_solar_plants": 41, "measure_solar_power_performance": 42, "my_user_id": 43, "nlu_fallback": 44, "out_of_scope": 45, "predicting_solar_power": 46, "proactive_detection": 47, "restart": 48, "roles_available_SolarBhai": 49, "safety_solar_power_plants": 50, "session_start": 51, "solar_loss": 52, "solar_underperformance": 53, "status_dashboard": 54, "summary_table_SolarBhai": 55, "summary_visualizations_SolarBhai": 56, "ticket_management": 57, "users_view_ticket_details": 58}, "action_name": {"action_listen": 0, "action_restart": 1, "action_session_start": 2, "action_default_fallback": 3, "action_deactivate_loop": 4, "action_revert_fallback_events": 5, "action_default_ask_affirmation": 6, "action_default_ask_rephrase": 7, "action_two_stage_fallback": 8, "action_unlikely_intent": 9, "action_back": 10, "...": 11, "action_extract_slots": 12, "action_consumption_details": 13, "action_utter_please_rephrase": 14, "action_answer_question": 15, "utter_SolarBhai_platform": 16, "utter_access_tickets_SolarBhai": 17, "utter_additional_information_for_sites": 18, "utter_ask_id": 19, "utter_ask_question": 20, "utter_assign_issues_to_team": 21, "utter_assigne_roles_SolarBhai": 22, "utter_benefits_solar_performance_management": 23, "utter_causes_solar_loss_1": 24, "utter_causes_solar_loss_2": 25, "utter_causes_solar_loss_3": 26, "utter_causes_solar_loss_4": 27, "utter_causes_solar_loss_5": 28, "utter_causes_solar_loss_6": 29, "utter_causes_solar_loss_7": 30, "utter_causes_underperformance_1": 31, "utter_causes_underperformance_2": 32, "utter_causes_underperformance_3": 33, "utter_causes_underperformance_4": 34, "utter_causes_underperformance_5": 35, "utter_cheer_up": 36, "utter_contribution_AI": 37, "utter_did_that_help": 38, "utter_factors_affect_generation_solar_power": 39, "utter_faq_benefits_of_solar_energy": 40, "utter_faq_solar_battery_storage": 41, "utter_faq_solar_energy_environmental_impact": 42, "utter_faq_solar_energy_future_outlook": 43, "utter_faq_solar_inverter_maintenance": 44, "utter_faq_solar_net_metering": 45, "utter_faq_solar_panel_cleaning_frequency": 46, "utter_faq_solar_panel_efficiency": 47, "utter_faq_solar_panel_installation_process": 48, "utter_faq_solar_panel_lifetime": 49, "utter_faq_solar_panel_maintenance": 50, "utter_faq_solar_panel_orientation": 51, "utter_faq_solar_panel_shading_issues": 52, "utter_faq_solar_power_incentives": 53, "utter_faq_types_of_solar_panels": 54, "utter_filter_display_additional_informations": 55, "utter_goodbye": 56, "utter_greet": 57, "utter_happy": 58, "utter_iamabot": 59, "utter_improve_solar_power_performance": 60, "utter_interact_with_tables": 61, "utter_issues_solar_inverters_1": 62, "utter_issues_solar_inverters_2": 63, "utter_issues_solar_inverters_3": 64, "utter_issues_solar_inverters_4": 65, "utter_key_performance_indicators": 66, "utter_losses_solar_power_plants": 67, "utter_measure_performance_solar_plants": 68, "utter_predicting_solar_power": 69, "utter_proactive_detection": 70, "utter_roles_available_SolarBhai": 71, "utter_safety_solar_power_plants": 72, "utter_solar_loss": 73, "utter_solar_underperformance": 74, "utter_status_dashboard": 75, "utter_summary_table_SolarBhai": 76, "utter_summary_visualizations_SolarBhai": 77, "utter_ticket_management": 78, "utter_users_view_ticket_details": 79, "utterrr_measure_solar_power_performance": 80}, "entities": {"question": 0, "user_id": 1}, "slots": {"user_id_0": 0, "question_0": 1}, "active_loop": {}}, "action_texts": [], "entity_tag_specs": []}, "max_history": 5, "remove_duplicates": true}